bakeit/__init__.py
bakeit/cli.py
bakeit/tests.py
bakeit/uploader.py
bakeit/version.py
bakeit-0.2.3.dist-info/LICENSE
bakeit-0.2.3.dist-info/METADATA
bakeit-0.2.3.dist-info/WHEEL
bakeit-0.2.3.dist-info/entry_points.txt
bakeit-0.2.3.dist-info/top_level.txt
bakeit-0.2.3.dist-info/RECORD
