Metadata-Version: 2.1
Name: bakeit
Version: 0.2.3
Summary: A command-line interface for Pastery, the best pastebin in the world.
Home-page: https://github.com/skorokithakis/bakeit/
Author: Stavros Korokithakis
Author-email: hi@stavros.io
License: MIT
Platform: UNKNOWN
Classifier: License :: OSI Approved :: MIT License
Classifier: Programming Language :: Python
Classifier: Programming Language :: Python :: 2.5
Classifier: Programming Language :: Python :: 2.6
Classifier: Programming Language :: Python :: 2.7
Classifier: Programming Language :: Python :: 3.2
Classifier: Programming Language :: Python :: 3.3
Classifier: Programming Language :: Python :: 3.4
Classifier: Topic :: Software Development :: Libraries :: Python Modules
Requires-Dist: pyperclip
Requires-Dist: requests
Requires-Dist: requests[security]
